paragrep/__init__.py
paragrep-3.3.0.data/data/man/paragrep.1
paragrep-3.3.0.dist-info/LICENSE
paragrep-3.3.0.dist-info/METADATA
paragrep-3.3.0.dist-info/WHEEL
paragrep-3.3.0.dist-info/entry_points.txt
paragrep-3.3.0.dist-info/top_level.txt
paragrep-3.3.0.dist-info/RECORD
