Metadata-Version: 2.1
Name: paragrep
Version: 3.3.0
Summary: Print paragraphs matching regular expressions
Home-page: http://software.clapper.org/paragrep/
Author: Brian M. Clapper
Author-email: bmc@clapper.org
License: BSD-style license
Classifier: Intended Audience :: Developers
Classifier: Intended Audience :: System Administrators
Classifier: License :: OSI Approved :: BSD License
Classifier: Programming Language :: Python
Classifier: Topic :: Text Processing :: Filters
Classifier: Topic :: Utilities
License-File: LICENSE
